{"heading":"HB02635","0":"AN ACT PROMOTING THE WELFARE OF WORKERS IN THE WELLNESS SPA, BEAUTY SALON, FITNESS GYM AND RELATED BUSINESSES BY FACILITATING THEIR MEMBERSHIP IN THE SSS, FURTHER AMENDING FOR THIS PURPOSE REPUBLIC ACT NO. 1161, AS AMENDED, OTHERWISE KNOWN AS THE SOCIAL SECURITY LAW, AND FOR OTHER PURPOSES","principal-authors":" MENDOZA, RAYMUND DEMOCRITO C.","primary-referral":" LABOR AND EMPLOYMENT","status":" Pending with the Committee on LABOR AND EMPLOYMENT since 2019-07-31","historyid":"#HB02635-18","docs":[{"doclabel":"[Text As Filed]","docurl":"congress.gov.ph\/legisdocs\/basic_18\/HB02635.pdf","fs":"exists"}],"history":"\u003Ctable width=\"auto\"  border=\"0\" cellspacing=\"0\" cellpadding=\"0\"\u003E\u003Ctr\u003E\u003Ctd colspan=3\u003EHouse Bill\/Resolution NO. \u003Cb\u003EHB02635\u003C\/b\u003E\u003C\/td\u003E\u003C\/tr\u003E\u003Ctr\u003E\u003Ctd colspan=3\u003EFULL TITLE : AN ACT PROMOTING THE WELFARE OF WORKERS IN THE WELLNESS SPA, BEAUTY SALON, FITNESS GYM AND RELATED BUSINESSES BY FACILITATING THEIR MEMBERSHIP IN THE SSS, FURTHER AMENDING FOR THIS PURPOSE REPUBLIC ACT NO. 1161, AS AMENDED, OTHERWISE KNOWN AS THE SOCIAL SECURITY LAW, AND FOR OTHER PURPOSES\u003C\/td\u003E\u003C\/tr\u003E\u003Ctr\u003E\u003Ctd colspan=3\u003EPRINCIPAL AUTHOR\/S : \u003Cb\u003EMENDOZA, RAYMUND DEMOCRITO C.\u003C\/b\u003E\u003C\/td\u003E\u003C\/tr\u003E\u003Ctr\u003E\u003Ctd colspan=3\u003EDATE FILED : 2019-07-24\u003C\/td\u003E\u003C\/tr\u003E\u003Ctr\u003E\u003Ctd colspan=3\u003ESIGNIFICANCE: NATIONAL\u003C\/td\u003E\u003C\/tr\u003E\u003Ctr\u003E\u003Ctd colspan=3\u003E\u003Cb\u003EACTIONS TAKEN BY THE COMMITTEE ON RULES\u003C\/b\u003E\u003C\/td\u003E\u003C\/tr\u003E\u003Ctr\u003E\u003Ctd colspan=3\u003EREFERRAL TO THE COMMITTEE ON LABOR AND EMPLOYMENT ON 2019-07-31\u003C\/td\u003E\u003C\/tr\u003E\u003C\/table\u003E"}