{"heading":"HB04293","0":"AN ACT FAST TRACKING COUNTRYSIDE DEVELOPMENT BY STRENGTHENING THE RESEARCH AND DEVELOPMENT THROUGH THE ESTABLISHMENT OF RESEARCH AND DEVELOPMENT OFFICE IN JH CERILLES STATE COLLEGE IN THE CAMPUSES OF MATI, SAN MIGUEL AND DUMINGAG, APPROPRIATING FUNDS THEREFORE AND FOR OTHER PURPOSES","principal-authors":" YU, DIVINA GRACE C.; BABASA, LEONARDO JR. L.; ","primary-referral":" HIGHER AND TECHNICAL EDUCATION","mother-bill statusstatus":" Approved on Second Reading on 2020-06-05 Substituted by HB06968","historyid":"#HB04293-18","docs":[{"doclabel":"[Text As Filed]","docurl":"congress.gov.ph\/legisdocs\/basic_18\/HB04293.pdf","fs":"exists"}],"history":"\u003Ctable width=\"auto\"  border=\"0\" cellspacing=\"0\" cellpadding=\"0\"\u003E\u003Ctr\u003E\u003Ctd colspan=3\u003EHouse Bill\/Resolution NO. \u003Cb\u003EHB04293\u003C\/b\u003E\u003C\/td\u003E\u003C\/tr\u003E\u003Ctr\u003E\u003Ctd colspan=3\u003EFULL TITLE : AN ACT FAST TRACKING COUNTRYSIDE DEVELOPMENT BY STRENGTHENING THE RESEARCH AND DEVELOPMENT THROUGH THE ESTABLISHMENT OF RESEARCH AND DEVELOPMENT OFFICE IN JH CERILLES STATE COLLEGE IN THE CAMPUSES OF MATI, SAN MIGUEL AND DUMINGAG, APPROPRIATING FUNDS THEREFORE AND FOR OTHER PURPOSES\u003C\/td\u003E\u003C\/tr\u003E\u003Ctr\u003E\u003Ctd colspan=3\u003EPRINCIPAL AUTHOR\/S : \u003Cb\u003EYU, DIVINA GRACE C., BABASA, LEONARDO JR. L.\u003C\/b\u003E\u003C\/td\u003E\u003C\/tr\u003E\u003Ctr\u003E\u003Ctd colspan=3\u003EDATE FILED : 2019-09-02\u003C\/td\u003E\u003C\/tr\u003E\u003Ctr\u003E\u003Ctd colspan=3\u003ESIGNIFICANCE: NATIONAL\u003C\/td\u003E\u003C\/tr\u003E\u003Ctr\u003E\u003Ctd colspan=3\u003E\u003Cb\u003EACTIONS TAKEN BY THE COMMITTEE\u003C\/b\u003E\u003C\/td\u003E\u003C\/tr\u003E\u003Ctr\u003E\u003Ctd colspan=3\u003ECOMMITEE HEARINGS\/ACTIONS:\u003C\/td\u003E\u003C\/tr\u003E\u003Ctr\u003E\u003Ctd colspan=3\u003E\u003Cb\u003E&nbsp&nbsp&nbsp&nbsp&nbsp&nbsp1. Measure approved by the Committee on 2019-11-25\u003C\/b\u003E\u003Ctr\u003E\u003Ctd colspan=3\u003EMOTHER BILL:&nbspHB06968\u003C\/td\u003E\u003C\/tr\u003E\u003Ctr\u003E\u003Ctd colspan=3\u003E\u003Cb\u003EACTIONS TAKEN BY THE COMMITTEE ON RULES\u003C\/b\u003E\u003C\/td\u003E\u003C\/tr\u003E\u003Ctr\u003E\u003Ctd colspan=3\u003EREFERRAL TO THE COMMITTEE ON HIGHER AND TECHNICAL EDUCATION ON 2019-09-09\u003C\/td\u003E\u003C\/tr\u003E\u003C\/table\u003E"}