{"heading":"HB01060","0":"AN ACT IMPOSING STIFFER PENALTIES FOR FALSIFICATION OF CERTIFICATES OF LAND TITLE OR ANY APPLICATION, DEED, INSTRUMENT OR SUPPORTING DOCUMENT, REASONABLY CONNECTED WITH AND CALCULATED TO CAUSE THE ISSUANCE OF A CERTIFICATE OF LAND TITLE, CLASSIFYING THE SAME AS A HEINOUS OFFENSE INVOLVING ECONOMIC SABOTAGE IF THE VALUE OR AGGREGATE VALUE OF THE LAND IS AT LEAST TEN MILLION PESOS (P10,000,000.00), AMENDING FOR THE PURPOSE ARTICLES 171 AND 172 OF ACT NO. 3815, AS AMENDED, OTHERWISE KNOWN AS, THE REVISED PENAL CODE AND FOR OTHER PURPOSES","principal-authors":" LOYOLA, DAHLIA A.","primary-referral":" JUSTICE","status":" Pending with the Committee on JUSTICE since 2019-07-24","historyid":"#HB01060-18","docs":[{"doclabel":"[Text As Filed]","docurl":"congress.gov.ph\/legisdocs\/basic_18\/HB01060.pdf","fs":"exists"}],"history":"\u003Ctable width=\"auto\"  border=\"0\" cellspacing=\"0\" cellpadding=\"0\"\u003E\u003Ctr\u003E\u003Ctd colspan=3\u003EHouse Bill\/Resolution NO. \u003Cb\u003EHB01060\u003C\/b\u003E\u003C\/td\u003E\u003C\/tr\u003E\u003Ctr\u003E\u003Ctd colspan=3\u003EFULL TITLE : AN ACT IMPOSING STIFFER PENALTIES FOR FALSIFICATION OF CERTIFICATES OF LAND TITLE OR ANY APPLICATION, DEED, INSTRUMENT OR SUPPORTING DOCUMENT, REASONABLY CONNECTED WITH AND CALCULATED TO CAUSE THE ISSUANCE OF A CERTIFICATE OF LAND TITLE, CLASSIFYING THE SAME AS A HEINOUS OFFENSE INVOLVING ECONOMIC SABOTAGE IF THE VALUE OR AGGREGATE VALUE OF THE LAND IS AT LEAST TEN MILLION PESOS (P10,000,000.00), AMENDING FOR THE PURPOSE ARTICLES 171 AND 172 OF ACT NO. 3815, AS AMENDED, OTHERWISE KNOWN AS, THE REVISED PENAL CODE AND FOR OTHER PURPOSES\u003C\/td\u003E\u003C\/tr\u003E\u003Ctr\u003E\u003Ctd colspan=3\u003EPRINCIPAL AUTHOR\/S : \u003Cb\u003ELOYOLA, DAHLIA A.\u003C\/b\u003E\u003C\/td\u003E\u003C\/tr\u003E\u003Ctr\u003E\u003Ctd colspan=3\u003EDATE FILED : 2019-07-02\u003C\/td\u003E\u003C\/tr\u003E\u003Ctr\u003E\u003Ctd colspan=3\u003ESIGNIFICANCE: NATIONAL\u003C\/td\u003E\u003C\/tr\u003E\u003Ctr\u003E\u003Ctd colspan=3\u003E\u003Cb\u003EACTIONS TAKEN BY THE COMMITTEE ON RULES\u003C\/b\u003E\u003C\/td\u003E\u003C\/tr\u003E\u003Ctr\u003E\u003Ctd colspan=3\u003EREFERRAL TO THE COMMITTEE ON JUSTICE ON 2019-07-24\u003C\/td\u003E\u003C\/tr\u003E\u003C\/table\u003E"}