{"heading":"HB05583","0":"AN ACT AUTHORIZING THE USE OF THE RICE SUBSIDY AS PROVIDED FOR UNDER THE PANTAWID PAMILYANG PILIPINO PROGRAM (4Ps) IN THE GENERAL APPROPRIATIONS ACT OF 2019 FOR THE PURCHASE OF PALAY FROM FARMERS, MANDATING FOR THE PURPOSE THE DEPARTMENT OF SOCIAL WELFARE AND DEVELOPMENT (DSWD), IN COORDINATION WITH THE DEPARTMENT OF AGRICULTURE (DA) AND THE NATIONAL FOOD AUTHORITY (NFA), TO BUY PALAY FROM LOCAL FARMERS, AND DISTRIBUTE RICE SUBSIDY IN THE FORM OF ACTUAL RICE, INSTEAD OF CASH ASSISTANCE, TO QUALIFIED BENEFICIARIES","principal-authors":" VILLAFUERTE, LUIS RAYMUND \"LRAY\" JR F.","primary-referral":" AGRICULTURE AND FOOD","mother-bill statusstatus":" Pending With Rules (Included in OB on 2020-03-11) Substituted by HB06558","historyid":"#HB05583-18","docs":[{"doclabel":"[Text As Filed]","docurl":"congress.gov.ph\/legisdocs\/basic_18\/HB05583.pdf","fs":"exists"}],"history":"\u003Ctable width=\"auto\"  border=\"0\" cellspacing=\"0\" cellpadding=\"0\"\u003E\u003Ctr\u003E\u003Ctd colspan=3\u003EHouse Bill\/Resolution NO. \u003Cb\u003EHB05583\u003C\/b\u003E\u003C\/td\u003E\u003C\/tr\u003E\u003Ctr\u003E\u003Ctd colspan=3\u003EFULL TITLE : AN ACT AUTHORIZING THE USE OF THE RICE SUBSIDY AS PROVIDED FOR UNDER THE PANTAWID PAMILYANG PILIPINO PROGRAM (4Ps) IN THE GENERAL APPROPRIATIONS ACT OF 2019 FOR THE PURCHASE OF PALAY FROM FARMERS, MANDATING FOR THE PURPOSE THE DEPARTMENT OF SOCIAL WELFARE AND DEVELOPMENT (DSWD), IN COORDINATION WITH THE DEPARTMENT OF AGRICULTURE (DA) AND THE NATIONAL FOOD AUTHORITY (NFA), TO BUY PALAY FROM LOCAL FARMERS, AND DISTRIBUTE RICE SUBSIDY IN THE FORM OF ACTUAL RICE, INSTEAD OF CASH ASSISTANCE, TO QUALIFIED BENEFICIARIES \u003C\/td\u003E\u003C\/tr\u003E\u003Ctr\u003E\u003Ctd colspan=3\u003EPRINCIPAL AUTHOR\/S : \u003Cb\u003EVILLAFUERTE, LUIS RAYMUND &quot;LRAY&quot; JR F.\u003C\/b\u003E\u003C\/td\u003E\u003C\/tr\u003E\u003Ctr\u003E\u003Ctd colspan=3\u003EDATE FILED : 2019-11-21\u003C\/td\u003E\u003C\/tr\u003E\u003Ctr\u003E\u003Ctd colspan=3\u003ESIGNIFICANCE: NATIONAL\u003C\/td\u003E\u003C\/tr\u003E\u003Ctr\u003E\u003Ctd colspan=3\u003ECO-AUTHORS (Journal Entries) :\u003C\/td\u003E\u003C\/tr\u003E\u003Ctr\u003E\u003Ctd\u003E1. Cabatbat (000 2020-01-30)\u003C\/td\u003E\u003Ctd\u003E2. Alonte (000 2020-02-03)\u003C\/td\u003E\u003Ctr\u003E\u003Ctd\u003E3. Tiangco (000 2020-02-19)\u003C\/td\u003E\u003Ctd\u003E4. Cari (000 2020-05-20)\u003C\/td\u003E\u003Ctr\u003E\u003Ctd\u003E5. Tambunting (000 2020-05-20)\u003C\/td\u003E\u003Ctr\u003E\u003Ctd colspan=3\u003E\u003Cb\u003EACTIONS TAKEN BY THE COMMITTEE\u003C\/b\u003E\u003C\/td\u003E\u003C\/tr\u003E\u003Ctr\u003E\u003Ctd colspan=3\u003ECOMMITEE HEARINGS\/ACTIONS:\u003C\/td\u003E\u003C\/tr\u003E\u003Ctr\u003E\u003Ctd colspan=3\u003E\u003Cb\u003E&nbsp&nbsp&nbsp&nbsp&nbsp&nbsp1. Deliberated upon by the Mother Committee on 2019-12-09\u003C\/b\u003E\u003Ctr\u003E\u003Ctd colspan=3\u003E&nbsp&nbsp&nbsp&nbsp&nbsp&nbsp&nbsp&nbsp&nbsp&nbsp-The Committee approved HB 5583 with amendments. The Committee Secretariat was instructed to prepare the substitute bill and submit the same to the Committee on Appropriation for comments.\u003C\/td\u003E\u003C\/tr\u003E\u003Ctr\u003E\u003Ctd colspan=3\u003E\u003Cb\u003E&nbsp&nbsp&nbsp&nbsp&nbsp&nbsp2. Transmitted to the Committee on Appropriations on 2019-12-18\u003C\/b\u003E\u003Ctr\u003E\u003Ctd colspan=3\u003E\u003Cb\u003E&nbsp&nbsp&nbsp&nbsp&nbsp&nbsp3. Scheduled for Deliberation by the Committee on Appropriations on 2020-01-16\u003C\/b\u003E\u003Ctr\u003E\u003Ctd colspan=3\u003EMOTHER BILL:&nbspHB06558\u003C\/td\u003E\u003C\/tr\u003E\u003Ctr\u003E\u003Ctd colspan=3\u003E\u003Cb\u003EACTIONS TAKEN BY THE COMMITTEE ON RULES\u003C\/b\u003E\u003C\/td\u003E\u003C\/tr\u003E\u003Ctr\u003E\u003Ctd colspan=3\u003EREFERRAL TO THE COMMITTEE ON AGRICULTURE AND FOOD ON 2019-11-27\u003C\/td\u003E\u003C\/tr\u003E\u003Ctr\u003E\u003Ctd colspan=3\u003ESECONDARILY REFERRED TO THE COMMITTEE(S) ON APPROPRIATIONS\u003C\/td\u003E\u003C\/tr\u003E\u003C\/table\u003E"}