{"heading":"HB00948","0":"AN ACT ESTABLISHING A NATIONAL HIGH SCHOOL IN BARANGAY SALVACION, CITY OF ORMOC IN THE PROVINCE OF LEYTE TO BE KNOWN AS SALVACION NATIONAL HIGH SCHOOL AND APPROPRIATING FUNDS THEREFOR","principal-authors":" TORRES-GOMEZ, LUCY","primary-referral":" BASIC EDUCATION AND CULTURE","status":" Pending with the Committee on BASIC EDUCATION AND CULTURE since 2019-07-24","historyid":"#HB00948-18","docs":[{"doclabel":"[Text As Filed]","docurl":"congress.gov.ph\/legisdocs\/basic_18\/hb00948.pdf","fs":"exists"}],"history":"\u003Ctable width=\"auto\"  border=\"0\" cellspacing=\"0\" cellpadding=\"0\"\u003E\u003Ctr\u003E\u003Ctd colspan=3\u003EHouse Bill\/Resolution NO. \u003Cb\u003EHB00948\u003C\/b\u003E\u003C\/td\u003E\u003C\/tr\u003E\u003Ctr\u003E\u003Ctd colspan=3\u003EFULL TITLE : AN ACT ESTABLISHING A NATIONAL HIGH SCHOOL IN BARANGAY SALVACION, CITY OF ORMOC IN THE PROVINCE OF LEYTE TO BE KNOWN AS SALVACION NATIONAL HIGH SCHOOL AND APPROPRIATING FUNDS THEREFOR\u003C\/td\u003E\u003C\/tr\u003E\u003Ctr\u003E\u003Ctd colspan=3\u003EPRINCIPAL AUTHOR\/S : \u003Cb\u003ETORRES-GOMEZ, LUCY\u003C\/b\u003E\u003C\/td\u003E\u003C\/tr\u003E\u003Ctr\u003E\u003Ctd colspan=3\u003EDATE FILED : 2019-07-02\u003C\/td\u003E\u003C\/tr\u003E\u003Ctr\u003E\u003Ctd colspan=3\u003ESIGNIFICANCE: LOCAL\u003C\/td\u003E\u003C\/tr\u003E\u003Ctr\u003E\u003Ctd colspan=3\u003ECO-AUTHORS (Journal Entries) :\u003C\/td\u003E\u003C\/tr\u003E\u003Ctr\u003E\u003Ctd\u003E1. Noel (000 2019-11-19)\u003C\/td\u003E\u003Ctr\u003E\u003Ctd colspan=3\u003E\u003Cb\u003EACTIONS TAKEN BY THE COMMITTEE ON RULES\u003C\/b\u003E\u003C\/td\u003E\u003C\/tr\u003E\u003Ctr\u003E\u003Ctd colspan=3\u003EREFERRAL TO THE COMMITTEE ON BASIC EDUCATION AND CULTURE ON 2019-07-24\u003C\/td\u003E\u003C\/tr\u003E\u003C\/table\u003E"}