{"heading":"HR00838","0":"RESOLUTION URGING THE APPROPRIATE GOVERNMENT AGENCIES TO CONDUCT COVID  19 TESTING TO ALL DRIVERS AND CONDUCTORS, AIRCRAFT PILOTS AND ITS CREW, SHIP CAPTAINS AND ITS CREW, RAIL\/LOCOMOTIVE PILOTS AND ITS CREW BEFORE ITS OPERATION AS PART OF THE MINIMUM PUBLIC HEALTH STANDARDS","principal-authors":" SAKALURAN, PRINCESS RIHAN M.","primary-referral":" DEFEAT COVID-19 AD-HOC COMMITTEE","status":" Pending with the Committee on DEFEAT COVID-19 AD-HOC COMMITTEE since 2020-05-11","historyid":"#HR00838-18","docs":[{"doclabel":"[Text As Filed]","docurl":"congress.gov.ph\/legisdocs\/basic_18\/HR00838.pdf","fs":"exists"}],"history":"\u003Ctable width=\"auto\"  border=\"0\" cellspacing=\"0\" cellpadding=\"0\"\u003E\u003Ctr\u003E\u003Ctd colspan=3\u003EHouse Bill\/Resolution NO. \u003Cb\u003EHR00838\u003C\/b\u003E\u003C\/td\u003E\u003C\/tr\u003E\u003Ctr\u003E\u003Ctd colspan=3\u003EFULL TITLE : RESOLUTION URGING THE APPROPRIATE GOVERNMENT AGENCIES TO CONDUCT COVID  19 TESTING TO ALL DRIVERS AND CONDUCTORS, AIRCRAFT PILOTS AND ITS CREW, SHIP CAPTAINS AND ITS CREW, RAIL\/LOCOMOTIVE PILOTS AND ITS CREW BEFORE ITS OPERATION AS PART OF THE MINIMUM PUBLIC HEALTH STANDARDS\u003C\/td\u003E\u003C\/tr\u003E\u003Ctr\u003E\u003Ctd colspan=3\u003EPRINCIPAL AUTHOR\/S : \u003Cb\u003ESAKALURAN, PRINCESS RIHAN M.\u003C\/b\u003E\u003C\/td\u003E\u003C\/tr\u003E\u003Ctr\u003E\u003Ctd colspan=3\u003EDATE FILED : 2020-05-06\u003C\/td\u003E\u003C\/tr\u003E\u003Ctr\u003E\u003Ctd colspan=3\u003ECO-AUTHORS (Journal Entries) :\u003C\/td\u003E\u003C\/tr\u003E\u003Ctr\u003E\u003Ctd\u003E1. Ba\u00f1as-Nograles (000 2020-05-19)\u003C\/td\u003E\u003Ctd\u003E2. Alonte (000 2020-06-11)\u003C\/td\u003E\u003Ctr\u003E\u003Ctd colspan=3\u003E\u003Cb\u003EACTIONS TAKEN BY THE COMMITTEE ON RULES\u003C\/b\u003E\u003C\/td\u003E\u003C\/tr\u003E\u003Ctr\u003E\u003Ctd colspan=3\u003EREFERRAL TO THE COMMITTEE ON DEFEAT COVID-19 AD-HOC COMMITTEE ON 2020-05-11\u003C\/td\u003E\u003C\/tr\u003E\u003C\/table\u003E"}