{"heading":"HB03648","0":"AN ACT PROVIDING FOR THE CREATION OF THE QUINCENTENNIAL COMMISSION TO COMMEMORATE THE FIRST CIRCUMNAVIGATION OF THE GLOBE, THE INTRODUCTION OF CHRISTIANITY AS A RELIGION IN THE PHILIPPINE ISLANDS AND MAGELLAN'S LANDING IN HOMONHON ON MARCH 19, 1521, APPROPRIATING FUNDS THEREFOR AND FOR OTHER PURPOSES","principal-authors":" SAVELLANO, DEOGRACIAS VICTOR B.","primary-referral":" GOVERNMENT REORGANIZATION","status":" Pending with the Committee on GOVERNMENT REORGANIZATION since 2016-09-26","historyid":"#HB03648-17","docs":[{"doclabel":"[Text As Filed]","docurl":"congress.gov.ph\/legisdocs\/basic_17\/HB03648.pdf"}],"history":"\u003Ctable width=\"auto\"  border=\"0\" cellspacing=\"0\" cellpadding=\"0\"\u003E\u003Ctr\u003E\u003Ctd colspan=3\u003EHouse Bill\/Resolution NO. \u003Cb\u003EHB03648\u003C\/b\u003E\u003C\/td\u003E\u003C\/tr\u003E\u003Ctr\u003E\u003Ctd colspan=3\u003EFULL TITLE : AN ACT PROVIDING FOR THE CREATION OF THE QUINCENTENNIAL COMMISSION TO COMMEMORATE THE FIRST CIRCUMNAVIGATION OF THE GLOBE, THE INTRODUCTION OF CHRISTIANITY AS A RELIGION IN THE PHILIPPINE ISLANDS AND MAGELLAN'S LANDING IN HOMONHON ON MARCH 19, 1521, APPROPRIATING FUNDS THEREFOR AND FOR OTHER PURPOSES\u003C\/td\u003E\u003C\/tr\u003E\u003Ctr\u003E\u003Ctd colspan=3\u003EPRINCIPAL AUTHOR\/S : \u003Cb\u003ESAVELLANO, DEOGRACIAS VICTOR B.\u003C\/b\u003E\u003C\/td\u003E\u003C\/tr\u003E\u003Ctr\u003E\u003Ctd colspan=3\u003EDATE FILED : 2016-09-19\u003C\/td\u003E\u003C\/tr\u003E\u003Ctr\u003E\u003Ctd colspan=3\u003ESIGNIFICANCE: NATIONAL\u003C\/td\u003E\u003C\/tr\u003E\u003Ctr\u003E\u003Ctd colspan=3\u003ENATURE : Reform\u003C\/td\u003E\u003C\/tr\u003E\u003Ctr\u003E\u003Ctd colspan=3\u003ECO-AUTHORS (Journal Entries) :\u003C\/td\u003E\u003C\/tr\u003E\u003Ctr\u003E\u003Ctd\u003E1. Mercado (028 2016-09-28)\u003C\/td\u003E\u003Ctr\u003E\u003Ctd colspan=3\u003E\u003Cb\u003EACTIONS TAKEN BY THE COMMITTEE ON RULES\u003C\/b\u003E\u003C\/td\u003E\u003C\/tr\u003E\u003Ctr\u003E\u003Ctd colspan=3\u003EREFERRAL TO THE COMMITTEE ON GOVERNMENT REORGANIZATION ON 2016-09-26\u003C\/td\u003E\u003C\/tr\u003E\u003C\/table\u003E"}