{"heading":"HB04486","0":"AN ACT ESTABLISHING A NATIONAL HIGH SCHOOL IN BARANGAY MANLILISID, MUNICIPALITY OF JAVIER, PROVINCE OF LEYTE TO BE KNOWN AS MANLILISID NATIONAL HIGH SCHOOL AND APPROPRIATING FUNDS THEREFOR","principal-authors":" CARI, JOSE CARLO L.","primary-referral":" BASIC EDUCATION AND CULTURE","mother-bill statusstatus":" Republic Act RA10979 enacted on 2018-03-06 Substituted by HB05803","historyid":"#HB04486-17","docs":[{"doclabel":"[Text As Filed]","docurl":"congress.gov.ph\/legisdocs\/basic_17\/HB04486.pdf"}],"history":"\u003Ctable width=\"auto\"  border=\"0\" cellspacing=\"0\" cellpadding=\"0\"\u003E\u003Ctr\u003E\u003Ctd colspan=3\u003EHouse Bill\/Resolution NO. \u003Cb\u003EHB04486\u003C\/b\u003E\u003C\/td\u003E\u003C\/tr\u003E\u003Ctr\u003E\u003Ctd colspan=3\u003EFULL TITLE : AN ACT ESTABLISHING A NATIONAL HIGH SCHOOL IN BARANGAY MANLILISID, MUNICIPALITY OF JAVIER, PROVINCE OF LEYTE TO BE KNOWN AS MANLILISID NATIONAL HIGH SCHOOL AND APPROPRIATING FUNDS THEREFOR\u003C\/td\u003E\u003C\/tr\u003E\u003Ctr\u003E\u003Ctd colspan=3\u003EPRINCIPAL AUTHOR\/S : \u003Cb\u003ECARI, JOSE CARLO L.\u003C\/b\u003E\u003C\/td\u003E\u003C\/tr\u003E\u003Ctr\u003E\u003Ctd colspan=3\u003EDATE FILED : 2016-11-22\u003C\/td\u003E\u003C\/tr\u003E\u003Ctr\u003E\u003Ctd colspan=3\u003ESIGNIFICANCE: LOCAL\u003C\/td\u003E\u003C\/tr\u003E\u003Ctr\u003E\u003Ctd colspan=3\u003ECO-AUTHORS (Journal Entries) :\u003C\/td\u003E\u003C\/tr\u003E\u003Ctr\u003E\u003Ctd\u003E1. Noel (084 2017-05-02)\u003C\/td\u003E\u003Ctr\u003E\u003Ctd colspan=3\u003E\u003Cb\u003EACTIONS TAKEN BY THE COMMITTEE\u003C\/b\u003E\u003C\/td\u003E\u003C\/tr\u003E\u003Ctr\u003E\u003Ctd colspan=3\u003ECOMMITEE HEARINGS\/ACTIONS:\u003C\/td\u003E\u003C\/tr\u003E\u003Ctr\u003E\u003Ctd colspan=3\u003E\u003Cb\u003E&nbsp&nbsp&nbsp&nbsp&nbsp&nbsp1. Scheduled for meeting\/hearing on 2017-03-14\u003C\/b\u003E\u003Ctr\u003E\u003Ctd colspan=3\u003E\u003Cb\u003E&nbsp&nbsp&nbsp&nbsp&nbsp&nbsp2. Approved by the Committee on 2017-03-14\u003C\/b\u003E\u003Ctr\u003E\u003Ctd colspan=3\u003E\u003Cb\u003E&nbsp&nbsp&nbsp&nbsp&nbsp&nbsp3. Committee Report Approved on 2017-03-14\u003C\/b\u003E\u003Ctr\u003E\u003Ctd colspan=3\u003E\u003Cb\u003E&nbsp&nbsp&nbsp&nbsp&nbsp&nbsp4. Transmitted to the Committee on Appropriations on 2017-04-17\u003C\/b\u003E\u003Ctr\u003E\u003Ctd colspan=3\u003E\u003Cb\u003E&nbsp&nbsp&nbsp&nbsp&nbsp&nbsp5. Approved by the Committee on Appropriations on 2017-05-02\u003C\/b\u003E\u003Ctr\u003E\u003Ctd colspan=3\u003E\u003Cb\u003E&nbsp&nbsp&nbsp&nbsp&nbsp&nbsp6. Approved by the Committee on Appropriations on 2017-05-02\u003C\/b\u003E\u003Ctr\u003E\u003Ctd colspan=3\u003E&nbsp&nbsp&nbsp&nbsp&nbsp&nbsp&nbsp&nbsp&nbsp&nbsp-Approved pursuant to Section 44 of the Rules of the House of Representatives, 17th Congress, without amendment.\u003C\/td\u003E\u003C\/tr\u003E\u003Ctr\u003E\u003Ctd colspan=3\u003E\u003Cb\u003E&nbsp&nbsp&nbsp&nbsp&nbsp&nbsp7. Committee Report filed on 2017-05-31\u003C\/b\u003E\u003Ctr\u003E\u003Ctd colspan=3\u003E&nbsp&nbsp&nbsp&nbsp&nbsp&nbsp&nbsp&nbsp&nbsp&nbsp-Committee Report No. 289 on House Bill No. 5803 in substitution of House Bill No. 4486.\u003C\/td\u003E\u003C\/tr\u003E\u003Ctr\u003E\u003Ctd colspan=3\u003EMOTHER BILL:&nbspHB05803\u003C\/td\u003E\u003C\/tr\u003E\u003Ctr\u003E\u003Ctd colspan=3\u003E\u003Cb\u003EACTIONS TAKEN BY THE COMMITTEE ON RULES\u003C\/b\u003E\u003C\/td\u003E\u003C\/tr\u003E\u003Ctr\u003E\u003Ctd colspan=3\u003EREFERRAL TO THE COMMITTEE ON BASIC EDUCATION AND CULTURE ON 2016-11-28\u003C\/td\u003E\u003C\/tr\u003E\u003C\/table\u003E"}