{"heading":"HB02565","0":"AN ACT SEEKING TO INCLUDE BARANGAY OFFICIALS IN THE COMPULSORY MEMBERSHIP OF THE GOVERNMENT SERVICE INSURANCE SYSTEM (GSIS), AMENDING FOR THIS PURPOSE RA 8291 AND APPROPRIATING FUNDS THEREFOR","principal-authors":" PALMA, WILTER \"SHARKY\" II WEE","primary-referral":" GOVERNMENT ENTERPRISES AND PRIVATIZATION","status":" Deliberated by the TWG on 2017-10-12","historyid":"#HB02565-17","docs":[{"doclabel":"[Text As Filed]","docurl":"congress.gov.ph\/legisdocs\/basic_17\/HB02565.pdf"}],"history":"\u003Ctable width=\"auto\"  border=\"0\" cellspacing=\"0\" cellpadding=\"0\"\u003E\u003Ctr\u003E\u003Ctd colspan=3\u003EHouse Bill\/Resolution NO. \u003Cb\u003EHB02565\u003C\/b\u003E\u003C\/td\u003E\u003C\/tr\u003E\u003Ctr\u003E\u003Ctd colspan=3\u003EFULL TITLE : AN ACT SEEKING TO INCLUDE BARANGAY OFFICIALS IN THE COMPULSORY MEMBERSHIP OF THE GOVERNMENT SERVICE INSURANCE SYSTEM (GSIS), AMENDING FOR THIS PURPOSE RA 8291 AND APPROPRIATING FUNDS THEREFOR\u003C\/td\u003E\u003C\/tr\u003E\u003Ctr\u003E\u003Ctd colspan=3\u003EPRINCIPAL AUTHOR\/S : \u003Cb\u003EPALMA, WILTER &quot;SHARKY&quot; II WEE\u003C\/b\u003E\u003C\/td\u003E\u003C\/tr\u003E\u003Ctr\u003E\u003Ctd colspan=3\u003EDATE FILED : 2016-08-04\u003C\/td\u003E\u003C\/tr\u003E\u003Ctr\u003E\u003Ctd colspan=3\u003ESIGNIFICANCE: NATIONAL\u003C\/td\u003E\u003C\/tr\u003E\u003Ctr\u003E\u003Ctd colspan=3\u003ENATURE : Reform\u003C\/td\u003E\u003C\/tr\u003E\u003Ctr\u003E\u003Ctd colspan=3\u003ECO-AUTHORS (Journal Entries) :\u003C\/td\u003E\u003C\/tr\u003E\u003Ctr\u003E\u003Ctd\u003E1. Robes (021 2016-09-13)\u003C\/td\u003E\u003Ctd\u003E2. Tupas (021 2016-09-13)\u003C\/td\u003E\u003Ctr\u003E\u003Ctd\u003E3. Pimentel (021 2016-09-13)\u003C\/td\u003E\u003Ctd\u003E4. Montoro (021 2016-09-13)\u003C\/td\u003E\u003Ctr\u003E\u003Ctd\u003E5. Olivarez (021 2016-09-13)\u003C\/td\u003E\u003Ctd\u003E6. Zubiri (022 2016-09-14)\u003C\/td\u003E\u003Ctr\u003E\u003Ctd\u003E7. Sy-Alvarado (022 2016-09-14)\u003C\/td\u003E\u003Ctd\u003E8. Go (M.) (022 2016-09-14)\u003C\/td\u003E\u003Ctr\u003E\u003Ctd\u003E9. Bautista-Bandigan (023 2016-09-19)\u003C\/td\u003E\u003Ctd\u003E10. Velasco-Catera (025 2016-09-21)\u003C\/td\u003E\u003Ctr\u003E\u003Ctd\u003E11. Lopez (M.L.) (025 2016-09-21)\u003C\/td\u003E\u003Ctd\u003E12. Hernandez (F.) (026 2016-09-26)\u003C\/td\u003E\u003Ctr\u003E\u003Ctd\u003E13. Matugas (027 2016-09-27)\u003C\/td\u003E\u003Ctd\u003E14. Nograles (J.J.) (034 2016-10-10)\u003C\/td\u003E\u003Ctr\u003E\u003Ctd\u003E15. Villafuerte (040 2016-11-07)\u003C\/td\u003E\u003Ctd\u003E16. Amante (000 2017-10-10)\u003C\/td\u003E\u003Ctr\u003E\u003Ctd colspan=3\u003E\u003Cb\u003EACTIONS TAKEN BY THE COMMITTEE\u003C\/b\u003E\u003C\/td\u003E\u003C\/tr\u003E\u003Ctr\u003E\u003Ctd colspan=3\u003ECOMMITEE HEARINGS\/ACTIONS:\u003C\/td\u003E\u003C\/tr\u003E\u003Ctr\u003E\u003Ctd colspan=3\u003E\u003Cb\u003E&nbsp&nbsp&nbsp&nbsp&nbsp&nbsp1. Deliberated upon by the Mother Committee on 2017-03-17\u003C\/b\u003E\u003Ctr\u003E\u003Ctd colspan=3\u003E&nbsp&nbsp&nbsp&nbsp&nbsp&nbsp&nbsp&nbsp&nbsp&nbsp-Creation of TWG on proposal to grant social security to barangay officials, chaired by Rep. Sharkee Palma\u003C\/td\u003E\u003C\/tr\u003E\u003Ctr\u003E\u003Ctd colspan=3\u003E\u003Cb\u003E&nbsp&nbsp&nbsp&nbsp&nbsp&nbsp2. Deliberated by the TWG on 2017-10-12\u003C\/b\u003E\u003Ctr\u003E\u003Ctd colspan=3\u003E&nbsp&nbsp&nbsp&nbsp&nbsp&nbsp&nbsp&nbsp&nbsp&nbsp-1st TWG on measures proposing to grant social security to barangay officials, chaired by Rep. Palma\u003C\/td\u003E\u003C\/tr\u003E\u003Ctr\u003E\u003Ctd colspan=3\u003E\u003Cb\u003EACTIONS TAKEN BY THE COMMITTEE ON RULES\u003C\/b\u003E\u003C\/td\u003E\u003C\/tr\u003E\u003Ctr\u003E\u003Ctd colspan=3\u003EREFERRAL TO THE COMMITTEE ON GOVERNMENT ENTERPRISES AND PRIVATIZATION ON 2016-08-10\u003C\/td\u003E\u003C\/tr\u003E\u003C\/table\u003E"}