{"heading":"HB07993","0":"AN ACT REGULATING ELECTRONIC CIGARETTES","principal-authors":" BARBERS, ROBERT ACE S.","primary-referral":" TRADE AND INDUSTRY","status":" Pending with the Committee on TRADE AND INDUSTRY since 2018-08-08","historyid":"#HB07993-17","docs":[{"doclabel":"[Text As Filed]","docurl":"congress.gov.ph\/legisdocs\/basic_17\/HB07993.pdf"}],"history":"\u003Ctable width=\"auto\"  border=\"0\" cellspacing=\"0\" cellpadding=\"0\"\u003E\u003Ctr\u003E\u003Ctd colspan=3\u003EHouse Bill\/Resolution NO. \u003Cb\u003EHB07993\u003C\/b\u003E\u003C\/td\u003E\u003C\/tr\u003E\u003Ctr\u003E\u003Ctd colspan=3\u003EFULL TITLE : AN ACT REGULATING ELECTRONIC CIGARETTES\u003C\/td\u003E\u003C\/tr\u003E\u003Ctr\u003E\u003Ctd colspan=3\u003EABSTRACT : Defines among others:  \u201cE-cigarette\u201d (product that can be used for the consumption of a nicotine-containing vapour) \u201cNicotine\u201d (nicotinic alkaloids, including any salt or complex of nicotine whether derived from tobacco or synthetically produced); \u201cVaping\u201d (act of using an e-cigarette).\r\nProvides that nicotine containers shall bear a textual health warnings \u201cThis product may damage your health and is addictive\u201d; and a retailer signage statement shall likewise be posted:  \u201cSALE\/DISTRIBUTION TO OR PURCHASE BY MINORS OF E-CIGARETTES IS UNLAWFUL\u201d or \u201cIT IS UNLAWFUL FOR E-CIGARETTES TO BE SOLD\/DISTRIBUTED TO OR PURCHASED BY PERSONS UNDER 18 YEARS OF AGE\u201d.\r\n\u003C\/td\u003E\u003C\/tr\u003E\u003Ctr\u003E\u003Ctd colspan=3\u003EPRINCIPAL AUTHOR\/S : \u003Cb\u003EBARBERS, ROBERT ACE S.\u003C\/b\u003E\u003C\/td\u003E\u003C\/tr\u003E\u003Ctr\u003E\u003Ctd colspan=3\u003EDATE FILED : 2018-08-01\u003C\/td\u003E\u003C\/tr\u003E\u003Ctr\u003E\u003Ctd colspan=3\u003ESIGNIFICANCE: NATIONAL\u003C\/td\u003E\u003C\/tr\u003E\u003Ctr\u003E\u003Ctd colspan=3\u003ECO-AUTHORS (Journal Entries) :\u003C\/td\u003E\u003C\/tr\u003E\u003Ctr\u003E\u003Ctd\u003E1. Sy-Alvarado (000 2018-08-16)\u003C\/td\u003E\u003Ctr\u003E\u003Ctd colspan=3\u003E\u003Cb\u003EACTIONS TAKEN BY THE COMMITTEE ON RULES\u003C\/b\u003E\u003C\/td\u003E\u003C\/tr\u003E\u003Ctr\u003E\u003Ctd colspan=3\u003EREFERRAL TO THE COMMITTEE ON TRADE AND INDUSTRY ON 2018-08-08\u003C\/td\u003E\u003C\/tr\u003E\u003Ctr\u003E\u003Ctd colspan=3\u003ESECONDARILY REFERRED TO THE COMMITTEE(S) ON HEALTH\u003C\/td\u003E\u003C\/tr\u003E\u003C\/table\u003E"}