{"heading":"HB08054","0":"AN ACT ESTABLISHING AN ELEMENTARY SCHOOL IN BARANGAY SAN ISIDRO, JARO, ILOILO CITY TO BE KNOWN AS THE SAN ISIDRO ELEMENTARY SCHOOL AND APPROPRIATING FUNDS THEREFOR","principal-authors":" TRE\u00d1AS, JERRY P.","primary-referral":" BASIC EDUCATION AND CULTURE","mother-bill statusstatus":" Republic Act RA11425 enacted on 2019-08-22 Substituted by HB08848","historyid":"#HB08054-17","docs":[{"doclabel":"[Text As Filed]","docurl":"congress.gov.ph\/legisdocs\/basic_17\/HB08054.pdf"}],"history":"\u003Ctable width=\"auto\"  border=\"0\" cellspacing=\"0\" cellpadding=\"0\"\u003E\u003Ctr\u003E\u003Ctd colspan=3\u003EHouse Bill\/Resolution NO. \u003Cb\u003EHB08054\u003C\/b\u003E\u003C\/td\u003E\u003C\/tr\u003E\u003Ctr\u003E\u003Ctd colspan=3\u003EFULL TITLE : AN ACT ESTABLISHING AN ELEMENTARY SCHOOL IN BARANGAY SAN ISIDRO, JARO, ILOILO CITY TO BE KNOWN AS THE SAN ISIDRO ELEMENTARY SCHOOL AND APPROPRIATING FUNDS THEREFOR\u003C\/td\u003E\u003C\/tr\u003E\u003Ctr\u003E\u003Ctd colspan=3\u003EPRINCIPAL AUTHOR\/S : \u003Cb\u003ETRE&Ntilde;AS, JERRY P.\u003C\/b\u003E\u003C\/td\u003E\u003C\/tr\u003E\u003Ctr\u003E\u003Ctd colspan=3\u003EDATE FILED : 2018-08-06\u003C\/td\u003E\u003C\/tr\u003E\u003Ctr\u003E\u003Ctd colspan=3\u003ESIGNIFICANCE: LOCAL\u003C\/td\u003E\u003C\/tr\u003E\u003Ctr\u003E\u003Ctd colspan=3\u003E\u003Cb\u003EACTIONS TAKEN BY THE COMMITTEE\u003C\/b\u003E\u003C\/td\u003E\u003C\/tr\u003E\u003Ctr\u003E\u003Ctd colspan=3\u003EMOTHER BILL:&nbspHB08848\u003C\/td\u003E\u003C\/tr\u003E\u003Ctr\u003E\u003Ctd colspan=3\u003E\u003Cb\u003EACTIONS TAKEN BY THE COMMITTEE ON RULES\u003C\/b\u003E\u003C\/td\u003E\u003C\/tr\u003E\u003Ctr\u003E\u003Ctd colspan=3\u003EREFERRAL TO THE COMMITTEE ON BASIC EDUCATION AND CULTURE ON 2018-08-08\u003C\/td\u003E\u003C\/tr\u003E\u003C\/table\u003E"}