{"heading":"HB04906","0":"AN ACT EXTENDING FOR ANOTHER TWENTY-FIVE (25) YEARS THE FRANCHISE GRANTED TO THE DELTA BROADCASTING SYSTEM, INC. TO ESTABLISH, MAINTAIN AND OPERATE RADIO AND TELEVISION BROADCASTING STATIONS WITHIN THE PHILIPPINES UNDER REPUBLIC ACT NO. 7723","principal-authors":" VELASCO, LORD ALLAN JAY Q.","primary-referral":" LEGISLATIVE FRANCHISES","mother-bill statusstatus":" Republic Act RA11303 enacted on 2019-04-17 Substituted by HB07199","historyid":"#HB04906-17","docs":[{"doclabel":"[Text As Filed]","docurl":"congress.gov.ph\/legisdocs\/basic_17\/HB04906.pdf"}],"history":"\u003Ctable width=\"auto\"  border=\"0\" cellspacing=\"0\" cellpadding=\"0\"\u003E\u003Ctr\u003E\u003Ctd colspan=3\u003EHouse Bill\/Resolution NO. \u003Cb\u003EHB04906\u003C\/b\u003E\u003C\/td\u003E\u003C\/tr\u003E\u003Ctr\u003E\u003Ctd colspan=3\u003EFULL TITLE : AN ACT EXTENDING FOR ANOTHER TWENTY-FIVE (25) YEARS THE FRANCHISE GRANTED TO THE DELTA BROADCASTING SYSTEM, INC. TO ESTABLISH, MAINTAIN AND OPERATE RADIO AND TELEVISION BROADCASTING STATIONS WITHIN THE PHILIPPINES UNDER REPUBLIC ACT NO. 7723\u003C\/td\u003E\u003C\/tr\u003E\u003Ctr\u003E\u003Ctd colspan=3\u003EPRINCIPAL AUTHOR\/S : \u003Cb\u003EVELASCO, LORD ALLAN JAY Q.\u003C\/b\u003E\u003C\/td\u003E\u003C\/tr\u003E\u003Ctr\u003E\u003Ctd colspan=3\u003EDATE FILED : 2017-02-01\u003C\/td\u003E\u003C\/tr\u003E\u003Ctr\u003E\u003Ctd colspan=3\u003ESIGNIFICANCE: NATIONAL\u003C\/td\u003E\u003C\/tr\u003E\u003Ctr\u003E\u003Ctd colspan=3\u003E\u003Cb\u003EACTIONS TAKEN BY THE COMMITTEE\u003C\/b\u003E\u003C\/td\u003E\u003C\/tr\u003E\u003Ctr\u003E\u003Ctd colspan=3\u003EMOTHER BILL:&nbspHB07199\u003C\/td\u003E\u003C\/tr\u003E\u003Ctr\u003E\u003Ctd colspan=3\u003E\u003Cb\u003EACTIONS TAKEN BY THE COMMITTEE ON RULES\u003C\/b\u003E\u003C\/td\u003E\u003C\/tr\u003E\u003Ctr\u003E\u003Ctd colspan=3\u003EREFERRAL TO THE COMMITTEE ON LEGISLATIVE FRANCHISES ON 2017-02-08\u003C\/td\u003E\u003C\/tr\u003E\u003C\/table\u003E"}