{"heading":"HB00273","0":"AN ACT PROVIDING FOR A LIGHT RAIL TRANSPORT (LRT) OR MONORAIL OR BUS RAPID TRANSIT (BRT) OR ANY OTHER APPROPRIATE MODERN MASS TRANSPORT SYSTEM IN CEBU CITY AND METRO CEBU","principal-authors":" DEL MAR, RAUL V.","primary-referral":" TRANSPORTATION","status":" Pending with the Committee on TRANSPORTATION since 2016-07-26","historyid":"#HB00273-17","docs":[{"doclabel":"[Text As Filed]","docurl":"congress.gov.ph\/legisdocs\/basic_17\/HB00273.pdf"}],"history":"\u003Ctable width=\"auto\"  border=\"0\" cellspacing=\"0\" cellpadding=\"0\"\u003E\u003Ctr\u003E\u003Ctd colspan=3\u003EHouse Bill\/Resolution NO. \u003Cb\u003EHB00273\u003C\/b\u003E\u003C\/td\u003E\u003C\/tr\u003E\u003Ctr\u003E\u003Ctd colspan=3\u003EFULL TITLE : AN ACT PROVIDING FOR A LIGHT RAIL TRANSPORT (LRT) OR MONORAIL OR BUS RAPID TRANSIT (BRT) OR ANY OTHER APPROPRIATE MODERN MASS TRANSPORT SYSTEM IN CEBU CITY AND METRO CEBU\u003C\/td\u003E\u003C\/tr\u003E\u003Ctr\u003E\u003Ctd colspan=3\u003EPRINCIPAL AUTHOR\/S : \u003Cb\u003EDEL MAR, RAUL V.\u003C\/b\u003E\u003C\/td\u003E\u003C\/tr\u003E\u003Ctr\u003E\u003Ctd colspan=3\u003EDATE FILED : 2016-06-30\u003C\/td\u003E\u003C\/tr\u003E\u003Ctr\u003E\u003Ctd colspan=3\u003ESIGNIFICANCE: LOCAL\u003C\/td\u003E\u003C\/tr\u003E\u003Ctr\u003E\u003Ctd colspan=3\u003ENATURE : Economic\u003C\/td\u003E\u003C\/tr\u003E\u003Ctr\u003E\u003Ctd colspan=3\u003E\u003Cb\u003EACTIONS TAKEN BY THE COMMITTEE ON RULES\u003C\/b\u003E\u003C\/td\u003E\u003C\/tr\u003E\u003Ctr\u003E\u003Ctd colspan=3\u003EREFERRAL TO THE COMMITTEE ON TRANSPORTATION ON 2016-07-26\u003C\/td\u003E\u003C\/tr\u003E\u003C\/table\u003E"}