{"heading":"HB09193","0":"AN ACT DECLARING THE DAO TREE LOCATED WITHIN A POCKET SECONDARY FOREST IN THE INTEGRATED FOREST MANAGEMENT AGREEMENT (IFMA) AREA OF THE E. PELAEZ RANCH IN BAYOMBONG, BARANGAY CUGMAN, CAGAYAN DE ORO CITY AS THE CAGAYAN DE ORO HERITAGE TREE AND A TOURIST ATTRACTION","short-title":"  Declaring The Dao Tree Located Within A Pocket Secondary Forest In The Integrated Forest Management Agreement (ifma) Area Of The E. Pelaez Ranch In Bayombong, Barangay Cugman, Cagayan De Oro City As The Cagayan De Oro Heritage Tree And A Tourist Attraction ","principal-authors":" RODRIGUEZ, MAXIMO JR.B.","primary-referral":" RULES","status":" Approved by the House on 2019-06-03, transmitted to the Senate on 2019-06-04 and received by the Senate on 2019-06-04","historyid":"#HB09193-17","docs":[{"doclabel":"[Committee Report]","docurl":"congress.gov.ph\/legisdocs\/first_17\/CR01319.pdf"},{"doclabel":"[Text As Engrossed]","docurl":"congress.gov.ph\/legisdocs\/third_17\/HBT9193.pdf"}],"history":"\u003Ctable width=\"auto\"  border=\"0\" cellspacing=\"0\" cellpadding=\"0\"\u003E\u003Ctr\u003E\u003Ctd colspan=3\u003EHouse Bill\/Resolution NO. \u003Cb\u003EHB09193\u003C\/b\u003E\u003C\/td\u003E\u003C\/tr\u003E\u003Ctr\u003E\u003Ctd colspan=3\u003EFULL TITLE : AN ACT DECLARING THE DAO TREE LOCATED WITHIN A POCKET SECONDARY FOREST IN THE INTEGRATED FOREST MANAGEMENT AGREEMENT (IFMA) AREA OF THE E. PELAEZ RANCH IN BAYOMBONG, BARANGAY CUGMAN, CAGAYAN DE ORO CITY AS THE CAGAYAN DE ORO HERITAGE TREE AND A TOURIST ATTRACTION \u003C\/td\u003E\u003C\/tr\u003E\u003Ctr\u003E\u003Ctd colspan=3\u003ESHORT TITLE :  Declaring The Dao Tree Located Within A Pocket Secondary Forest In The Integrated Forest Management Agreement (ifma) Area Of The E. Pelaez Ranch In Bayombong, Barangay Cugman, Cagayan De Oro City As The Cagayan De Oro Heritage Tree And A Tourist Attraction \u003C\/td\u003E\u003C\/tr\u003E\u003Ctr\u003E\u003Ctd colspan=3\u003EPRINCIPAL AUTHOR\/S : \u003Cb\u003ERODRIGUEZ, MAXIMO JR.B.\u003C\/b\u003E\u003C\/td\u003E\u003C\/tr\u003E\u003Ctr\u003E\u003Ctd colspan=3\u003EDATE FILED : 2019-05-21\u003C\/td\u003E\u003C\/tr\u003E\u003Ctr\u003E\u003Ctd colspan=3\u003ESIGNIFICANCE: LOCAL\u003C\/td\u003E\u003C\/tr\u003E\u003Ctr\u003E\u003Ctd colspan=3\u003EAUTHORS(Final\/Third Reading) :\u003C\/td\u003E\u003C\/tr\u003E\u003Ctr\u003E\u003Ctd width='%33'\u003E1. Rodriguez (M.)\u003C\/td\u003E\u003Ctd width='33%'\u003E2. Nieto\u003C\/td\u003E\u003Ctr\u003E\u003Ctd colspan=3\u003E\u003Cb\u003EACTIONS TAKEN BY THE COMMITTEE\u003C\/b\u003E\u003C\/td\u003E\u003C\/tr\u003E\u003Ctr\u003E\u003Ctd colspan=3\u003ECOMMITTEE REPORT NO.&nbsp01319\u003C\/td\u003E\u003C\/tr\u003E\u003Ctr\u003E\u003Ctd colspan=3\u003ESUBMITTED ON 2019-05-21\u003C\/td\u003E\u003C\/tr\u003E\u003Ctr\u003E\u003Ctd colspan=3\u003ESUBMITTED BY:&nbspTOURISM, APPROPRIATIONS\u003C\/td\u003E\u003C\/tr\u003E\u003Ctr\u003E\u003Ctd colspan=3\u003ERECOMMENDATIONS:&nbspApproval in substitution of House Bill No. 7562\u003C\/td\u003E\u003C\/tr\u003E\u003Ctr\u003E\u003Ctd colspan=3\u003ESUBSTITUTED BILLS:&nbspHB07562\u003C\/td\u003E\u003C\/tr\u003E\u003Ctr\u003E\u003Ctd colspan=3\u003E\u003Cb\u003EACTIONS TAKEN BY THE COMMITTEE ON RULES\u003C\/b\u003E\u003C\/td\u003E\u003C\/tr\u003E\u003Ctr\u003E\u003Ctd colspan=3\u003EREFERRAL TO THE COMMITTEE ON RULES ON 2019-05-21\u003C\/td\u003E\u003C\/tr\u003E\u003Ctr\u003E\u003Ctd colspan=3\u003EDATE INCLUDED IN OB:&nbsp2019-05-21\u003C\/td\u003E\u003C\/tr\u003E\u003Ctr\u003E\u003Ctd colspan=3\u003EBUSINESS FOR THU\/FRI ON:&nbsp2019-05-28\u003C\/td\u003E\u003C\/tr\u003E\u003Ctr\u003E\u003Ctd colspan=3\u003E\u003Cb\u003ESECOND READING INFORMATION\u003C\/b\u003E\u003Cbr \/\u003E\u003Ctr\u003E\u003Ctd colspan=3\u003EPERIOD OF SPONSORSHIP :&nbsp2019-05-28\u003C\/td\u003E\u003C\/tr\u003E\u003Ctr\u003E\u003Ctd colspan=3\u003ESPONSORED BY :&nbsp Rodriguez (M.)\u003C\/td\u003E\u003C\/tr\u003E\u003Ctr\u003E\u003Ctd colspan=3\u003EFINAL LIST OF AUTHORS :&nbspRodriguez (M.), Nieto\u003C\/td\u003E\u003C\/tr\u003E\u003Ctr\u003E\u003Ctd colspan=3\u003EDATE APPROVED ON SECOND READING :&nbsp2019-05-28\u003C\/td\u003E\u003C\/tr\u003E\u003Ctr\u003E\u003Ctd colspan=3\u003E\u003Cb\u003ETHIRD READING INFORMATION\u003C\/b\u003E\u003C\/td\u003E\u003C\/tr\u003E\u003Ctr\u003E\u003Ctd colspan=3\u003EDATE COPY DISTRIBUTED TO MEMBERS:&nbsp2019-05-29\u003C\/td\u003E\u003C\/tr\u003E\u003Ctr\u003E\u003Ctd colspan=3\u003EDATE APPROVED BY THE HOUSE ON THIRD READING :2019-06-03\u003C\/td\u003E\u003C\/tr\u003E\u003Ctr\u003E\u003Ctd\u003EHOUSE VOTES:&nbsp;&nbsp;&nbsp;&nbsp;YEAS:187&nbsp;&nbsp;&nbsp;&nbsp; NAYS:0&nbsp;&nbsp;&nbsp;&nbsp;ABSTAIN:.0\u003Ctr\u003E\u003Ctd colspan=3\u003EDATE TRANSMITTED TO THE SENATE: &nbsp2019-06-04\u003C\/td\u003E\u003C\/tr\u003E\u003Ctr\u003E\u003Ctd colspan=3\u003E\u003Cb\u003EACTIONS TAKEN BY THE SENATE\/HOUSE\u003C\/b\u003E\u003C\/td\u003E\u003C\/tr\u003E\u003Ctr\u003E\u003Ctd colspan=3\u003EDATE RECEIVED BY THE SENATE: &nbsp2019-06-04\u003C\/td\u003E\u003C\/tr\u003E\u003Ctr\u003E\u003Ctd colspan=3\u003EREMARKS :&nbsp    \u003C\/td\u003E\u003C\/tr\u003E\u003C\/table\u003E"}