{"heading":"HR00737","0":"A RESOLUTION COMMENDING THE DEPARTMENT OF TOURISM FOR SPEARHEADING THE WELL-PLANNED, COORDINATED, AND EXECUTED HOSTING  OF THE 2016 MISS UNIVERSE PAGEANT","principal-authors":" ROCAMORA, RAMON V.A. \"RAV\"; ROMUALDEZ, YEDDA MARIE K.; ","primary-referral":" TOURISM","status":" Adopted as Resolution No. HR00064 on 2017-08-16","historyid":"#HR00737-17","docs":[{"doclabel":"[Committee Report]","docurl":"congress.gov.ph\/legisdocs\/first_17\/CR00165.pdf"},{"doclabel":"[Text As Filed]","docurl":"congress.gov.ph\/legisdocs\/basic_17\/HR00737.pdf"},{"doclabel":"[Adapted Resolution\/RBH]","docurl":"congress.gov.ph\/legisdocs\/second_17\/HR00737.pdf"}],"history":"\u003Ctable width=\"auto\"  border=\"0\" cellspacing=\"0\" cellpadding=\"0\"\u003E\u003Ctr\u003E\u003Ctd colspan=3\u003EHouse Bill\/Resolution NO. \u003Cb\u003EHR00737\u003C\/b\u003E\u003C\/td\u003E\u003C\/tr\u003E\u003Ctr\u003E\u003Ctd colspan=3\u003EADOPTED AS RESOLUTION NO. \u003Cb\u003EHR00064\u003C\/b\u003E\u003C\/td\u003E\u003C\/tr\u003E\u003Ctr\u003E\u003Ctd colspan=3\u003EFULL TITLE : A RESOLUTION COMMENDING THE DEPARTMENT OF TOURISM FOR SPEARHEADING THE WELL-PLANNED, COORDINATED, AND EXECUTED HOSTING  OF THE 2016 MISS UNIVERSE PAGEANT\u003C\/td\u003E\u003C\/tr\u003E\u003Ctr\u003E\u003Ctd colspan=3\u003EPRINCIPAL AUTHOR\/S : \u003Cb\u003EROCAMORA, RAMON V.A. &quot;RAV&quot;, ROMUALDEZ, YEDDA MARIE K.\u003C\/b\u003E\u003C\/td\u003E\u003C\/tr\u003E\u003Ctr\u003E\u003Ctd colspan=3\u003EDATE FILED : 2017-01-31\u003C\/td\u003E\u003C\/tr\u003E\u003Ctr\u003E\u003Ctd colspan=3\u003ECO-AUTHORS (Journal Entries) :\u003C\/td\u003E\u003C\/tr\u003E\u003Ctr\u003E\u003Ctd\u003E1. Gullas (084 2017-05-02)\u003C\/td\u003E\u003Ctd\u003E2. Nieto (010 2017-08-14)\u003C\/td\u003E\u003Ctr\u003E\u003Ctd colspan=3\u003EAUTHORS(Committee Report) :\u003C\/td\u003E\u003C\/tr\u003E\u003Ctr\u003E\u003Ctd width='%33'\u003E1. Rocamora\u003C\/td\u003E\u003Ctd width='33%'\u003E2. Romualdez\u003C\/td\u003E\u003Ctr\u003E\u003Ctd colspan=3\u003E\u003Cb\u003EACTIONS TAKEN BY THE COMMITTEE\u003C\/b\u003E\u003C\/td\u003E\u003C\/tr\u003E\u003Ctr\u003E\u003Ctd colspan=3\u003ECOMMITTEE REPORT NO.&nbsp00165\u003C\/td\u003E\u003C\/tr\u003E\u003Ctr\u003E\u003Ctd colspan=3\u003ESUBMITTED ON 2017-03-13\u003C\/td\u003E\u003C\/tr\u003E\u003Ctr\u003E\u003Ctd colspan=3\u003ESUBMITTED BY:&nbspTOURISM\u003C\/td\u003E\u003C\/tr\u003E\u003Ctr\u003E\u003Ctd colspan=3\u003ERECOMMENDATIONS:&nbspAdoption without amendment, in consolidation with HR No. 730\u003C\/td\u003E\u003C\/tr\u003E\u003Ctr\u003E\u003Ctd colspan=3\u003ECOMMITTEE REPORT AUTHORS :&nbspROCAMORA, RAMON V.A. \"RAV\", ROMUALDEZ, YEDDA MARIE K.\u003C\/td\u003E\u003C\/tr\u003E\u003Ctr\u003E\u003Ctd colspan=3\u003ECONSOLIDATED BILLS:&nbspHR00730\u003C\/td\u003E\u003C\/tr\u003E\u003Ctr\u003E\u003Ctd colspan=3\u003ECONSOLIDATED BILLS:&nbspHR00730\u003C\/td\u003E\u003C\/tr\u003E\u003Ctr\u003E\u003Ctd colspan=3\u003E\u003Cb\u003EACTIONS TAKEN BY THE COMMITTEE ON RULES\u003C\/b\u003E\u003C\/td\u003E\u003C\/tr\u003E\u003Ctr\u003E\u003Ctd colspan=3\u003EREFERRAL TO THE COMMITTEE ON TOURISM ON 2017-02-07\u003C\/td\u003E\u003C\/tr\u003E\u003Ctr\u003E\u003Ctd colspan=3\u003EDATE INCLUDED IN OB:&nbsp2017-03-13\u003C\/td\u003E\u003C\/tr\u003E\u003Ctr\u003E\u003Ctd colspan=3\u003EDATE CALENDARED :&nbsp2017-03-14\u003C\/td\u003E\u003C\/tr\u003E\u003Ctr\u003E\u003Ctd colspan=3\u003E\u003Cb\u003ESECOND READING INFORMATION\u003C\/b\u003E\u003Cbr \/\u003E\u003Ctr\u003E\u003Ctd colspan=3\u003EPERIOD OF SPONSORSHIP :&nbsp2017-08-16\u003C\/td\u003E\u003C\/tr\u003E\u003Ctr\u003E\u003Ctd colspan=3\u003ESPONSORED BY :&nbsp Hofer\u003C\/td\u003E\u003C\/tr\u003E\u003Ctr\u003E\u003Ctd colspan=3\u003ERESOLUTION ADOPTED ON SECOND READING :&nbsp2017-08-16\u003C\/td\u003E\u003C\/tr\u003E\u003Ctr\u003E\u003Ctd colspan=3\u003ENEW RESOLUTION NO. :&nbspHR00064\u003C\/td\u003E\u003C\/tr\u003E\u003Ctr\u003E\u003Ctd colspan=3\u003EADOPTED RESOLUTION TITLE:&nbspA RESOLUTION COMMENDING THE DEPARTMENT OF TOURISM FOR SPEARHEADING THE WELL-PLANNED, COORDINATED, AND EXECUTED HOSTING OF THE 2016 MISS UNIVERSE PAGEANT\u003C\/td\u003E\u003C\/tr\u003E\u003Ctr\u003E\u003Ctd colspan=3\u003EREMARKS :&nbsp  \u003C\/td\u003E\u003C\/tr\u003E\u003C\/table\u003E"}