{"heading":"HR01285","0":"RESOLUTION RECOGNIZING, COMMENDING AND EXPRESSING CONGRATULATIONS TO BUENAVISTA DEVELOPMENT COOPERATIVE (AGRICULTURE BASED) OF GUIMARAS AND SACRED HEART SAVINGS COOPERATIVE (NON-AGRICULTURE BASED) OF GALIMUYOD, ILOCOS SUR FOR WINNING THE 2017 LANDBANK GAWAD SA PINAKATANGING KOOPERATIBA (GAWAD PITAK) HALL OF FAME AWARD HELD LAST AUGUST 14, 2017 AT PHILIPPINE CONVENTION CENTER,  PASAY CITY","principal-authors":" GERON, RICO B.; BRAVO, ANTHONY M., Ph.D.; CANAMA, SABINIANO S.; ","primary-referral":" COOPERATIVES DEVELOPMENT","mother-bill statusstatus":" Adopted as Resolution No. HR00105 on 2018-01-23 Substituted by HR01559","historyid":"#HR01285-17","docs":[{"doclabel":"[Text As Filed]","docurl":"congress.gov.ph\/legisdocs\/basic_17\/HR01285.pdf"}],"history":"\u003Ctable width=\"auto\"  border=\"0\" cellspacing=\"0\" cellpadding=\"0\"\u003E\u003Ctr\u003E\u003Ctd colspan=3\u003EHouse Bill\/Resolution NO. \u003Cb\u003EHR01285\u003C\/b\u003E\u003C\/td\u003E\u003C\/tr\u003E\u003Ctr\u003E\u003Ctd colspan=3\u003EFULL TITLE : RESOLUTION RECOGNIZING, COMMENDING AND EXPRESSING CONGRATULATIONS TO BUENAVISTA DEVELOPMENT COOPERATIVE (AGRICULTURE BASED) OF GUIMARAS AND SACRED HEART SAVINGS COOPERATIVE (NON-AGRICULTURE BASED) OF GALIMUYOD, ILOCOS SUR FOR WINNING THE 2017 LANDBANK GAWAD SA PINAKATANGING KOOPERATIBA (GAWAD PITAK) HALL OF FAME AWARD HELD LAST AUGUST 14, 2017 AT PHILIPPINE CONVENTION CENTER,  PASAY CITY\u003C\/td\u003E\u003C\/tr\u003E\u003Ctr\u003E\u003Ctd colspan=3\u003EPRINCIPAL AUTHOR\/S : \u003Cb\u003EGERON, RICO B., BRAVO, ANTHONY M., Ph.D., CANAMA, SABINIANO S.\u003C\/b\u003E\u003C\/td\u003E\u003C\/tr\u003E\u003Ctr\u003E\u003Ctd colspan=3\u003EDATE FILED : 2017-09-06\u003C\/td\u003E\u003C\/tr\u003E\u003Ctr\u003E\u003Ctd colspan=3\u003E\u003Cb\u003EACTIONS TAKEN BY THE COMMITTEE\u003C\/b\u003E\u003C\/td\u003E\u003C\/tr\u003E\u003Ctr\u003E\u003Ctd colspan=3\u003EMOTHER BILL:&nbspHR01559\u003C\/td\u003E\u003C\/tr\u003E\u003Ctr\u003E\u003Ctd colspan=3\u003E\u003Cb\u003EACTIONS TAKEN BY THE COMMITTEE ON RULES\u003C\/b\u003E\u003C\/td\u003E\u003C\/tr\u003E\u003Ctr\u003E\u003Ctd colspan=3\u003EREFERRAL TO THE COMMITTEE ON COOPERATIVES DEVELOPMENT ON 2017-09-08\u003C\/td\u003E\u003C\/tr\u003E\u003C\/table\u003E"}