{"heading":"HR02055","0":"RESOLUTION URGING PRESIDENT RODRIGO R. DUTERTE TO INVITE REGIONAL AND NATIONAL STAKEHOLDERS TO A CONSULTATIVE ASSEMBLY IN PREPARATION FOR THE COMMEMORATION OF THE QUINCENTENNIAL ARRIVAL OF FERDINAND MAGELLAN IN THE PHILIPPINES","principal-authors":" GOMEZ, LUCY T.; DURANO, RAMON \"RED\" VI H.; ","primary-referral":" RULES","status":" Adopted as Resolution No. HR00145 on 2018-09-11","historyid":"#HR02055-17","docs":[{"doclabel":"[Committee Report]","docurl":"congress.gov.ph\/legisdocs\/first_17\/CR00810.pdf"},{"doclabel":"[Adapted Resolution\/RBH]","docurl":"congress.gov.ph\/legisdocs\/second_17\/HR02055.pdf"}],"history":"\u003Ctable width=\"auto\"  border=\"0\" cellspacing=\"0\" cellpadding=\"0\"\u003E\u003Ctr\u003E\u003Ctd colspan=3\u003EHouse Bill\/Resolution NO. \u003Cb\u003EHR02055\u003C\/b\u003E\u003C\/td\u003E\u003C\/tr\u003E\u003Ctr\u003E\u003Ctd colspan=3\u003EADOPTED AS RESOLUTION NO. \u003Cb\u003EHR00145\u003C\/b\u003E\u003C\/td\u003E\u003C\/tr\u003E\u003Ctr\u003E\u003Ctd colspan=3\u003EFULL TITLE : RESOLUTION URGING PRESIDENT RODRIGO R. DUTERTE TO INVITE REGIONAL AND NATIONAL STAKEHOLDERS TO A CONSULTATIVE ASSEMBLY IN PREPARATION FOR THE COMMEMORATION OF THE QUINCENTENNIAL ARRIVAL OF FERDINAND MAGELLAN IN THE PHILIPPINES\u003C\/td\u003E\u003C\/tr\u003E\u003Ctr\u003E\u003Ctd colspan=3\u003EPRINCIPAL AUTHOR\/S : \u003Cb\u003EGOMEZ, LUCY T., DURANO, RAMON &quot;RED&quot; VI H.\u003C\/b\u003E\u003C\/td\u003E\u003C\/tr\u003E\u003Ctr\u003E\u003Ctd colspan=3\u003EDATE FILED : 2018-08-06\u003C\/td\u003E\u003C\/tr\u003E\u003Ctr\u003E\u003Ctd colspan=3\u003ECO-AUTHORS (Journal Entries) :\u003C\/td\u003E\u003C\/tr\u003E\u003Ctr\u003E\u003Ctd\u003E1. Savellano (000 2018-08-15)\u003C\/td\u003E\u003Ctr\u003E\u003Ctd colspan=3\u003E\u003Cb\u003EACTIONS TAKEN BY THE COMMITTEE\u003C\/b\u003E\u003C\/td\u003E\u003C\/tr\u003E\u003Ctr\u003E\u003Ctd colspan=3\u003ECOMMITTEE REPORT NO.&nbsp00810\u003C\/td\u003E\u003C\/tr\u003E\u003Ctr\u003E\u003Ctd colspan=3\u003ESUBMITTED ON 2018-08-06\u003C\/td\u003E\u003C\/tr\u003E\u003Ctr\u003E\u003Ctd colspan=3\u003ESUBMITTED BY:&nbspBASIC EDUCATION AND CULTURE\u003C\/td\u003E\u003C\/tr\u003E\u003Ctr\u003E\u003Ctd colspan=3\u003ERECOMMENDATIONS:&nbspRecommending its adoption in substitution of House Resolution No. 1232\u003C\/td\u003E\u003C\/tr\u003E\u003Ctr\u003E\u003Ctd colspan=3\u003ESUBSTITUTED BILLS:&nbspHR01232\u003C\/td\u003E\u003C\/tr\u003E\u003Ctr\u003E\u003Ctd colspan=3\u003E\u003Cb\u003EACTIONS TAKEN BY THE COMMITTEE ON RULES\u003C\/b\u003E\u003C\/td\u003E\u003C\/tr\u003E\u003Ctr\u003E\u003Ctd colspan=3\u003EREFERRAL TO THE COMMITTEE ON RULES ON 2018-08-07\u003C\/td\u003E\u003C\/tr\u003E\u003Ctr\u003E\u003Ctd colspan=3\u003EDATE INCLUDED IN OB:&nbsp2018-08-07\u003C\/td\u003E\u003C\/tr\u003E\u003Ctr\u003E\u003Ctd colspan=3\u003EDATE CALENDARED :&nbsp2018-08-14\u003C\/td\u003E\u003C\/tr\u003E\u003Ctr\u003E\u003Ctd colspan=3\u003E\u003Cb\u003ESECOND READING INFORMATION\u003C\/b\u003E\u003Cbr \/\u003E\u003Ctr\u003E\u003Ctd colspan=3\u003ERESOLUTION ADOPTED ON SECOND READING :&nbsp2018-09-11\u003C\/td\u003E\u003C\/tr\u003E\u003Ctr\u003E\u003Ctd colspan=3\u003ENEW RESOLUTION NO. :&nbspHR00145\u003C\/td\u003E\u003C\/tr\u003E\u003Ctr\u003E\u003Ctd colspan=3\u003EADOPTED RESOLUTION TITLE:&nbspRESOLUTION URGING PRESIDENT RODRIGO R. DUTERTE TO INVITE REGIONAL AND NATIONAL STAKEHOLDERS TO A CONSULTATIVE ASSEMBLY IN PREPARATION FOR THE COMMEMORATION OF THE QUINCENTENNIAL ARRIVAL OF FERDINAND MAGELLAN IN THE PHILIPPINES\u003C\/td\u003E\u003C\/tr\u003E\u003C\/table\u003E"}