{"heading":"HR02308","0":"RESOLUTION DIRECTING THE ECONOMIC MANAGERS TO REVISIT SUGGESTED RETAIL PRICES OF BASIC COMMODITIES  FOR POSSIBLE ROLLBACK IN VIEW OF THE DECLINING GLOBAL CRUDE OIL PRICES","principal-authors":" CUA, DAKILA CARLO E.","primary-referral":" TRADE AND INDUSTRY","status":" Pending with the Committee on TRADE AND INDUSTRY since 2018-11-26","historyid":"#HR02308-17","docs":[{"doclabel":"[Text As Filed]","docurl":"congress.gov.ph\/legisdocs\/basic_17\/HR02308.pdf"}],"history":"\u003Ctable width=\"auto\"  border=\"0\" cellspacing=\"0\" cellpadding=\"0\"\u003E\u003Ctr\u003E\u003Ctd colspan=3\u003EHouse Bill\/Resolution NO. \u003Cb\u003EHR02308\u003C\/b\u003E\u003C\/td\u003E\u003C\/tr\u003E\u003Ctr\u003E\u003Ctd colspan=3\u003EFULL TITLE : RESOLUTION DIRECTING THE ECONOMIC MANAGERS TO REVISIT SUGGESTED RETAIL PRICES OF BASIC COMMODITIES  FOR POSSIBLE ROLLBACK IN VIEW OF THE DECLINING GLOBAL CRUDE OIL PRICES\u003C\/td\u003E\u003C\/tr\u003E\u003Ctr\u003E\u003Ctd colspan=3\u003EPRINCIPAL AUTHOR\/S : \u003Cb\u003ECUA, DAKILA CARLO E.\u003C\/b\u003E\u003C\/td\u003E\u003C\/tr\u003E\u003Ctr\u003E\u003Ctd colspan=3\u003EDATE FILED : 2018-11-20\u003C\/td\u003E\u003C\/tr\u003E\u003Ctr\u003E\u003Ctd colspan=3\u003ECO-AUTHORS (Journal Entries) :\u003C\/td\u003E\u003C\/tr\u003E\u003Ctr\u003E\u003Ctd\u003E1. Del Mar (000 2018-12-03)\u003C\/td\u003E\u003Ctr\u003E\u003Ctd colspan=3\u003E\u003Cb\u003EACTIONS TAKEN BY THE COMMITTEE ON RULES\u003C\/b\u003E\u003C\/td\u003E\u003C\/tr\u003E\u003Ctr\u003E\u003Ctd colspan=3\u003EREFERRAL TO THE COMMITTEE ON TRADE AND INDUSTRY ON 2018-11-26\u003C\/td\u003E\u003C\/tr\u003E\u003C\/table\u003E"}