{"heading":"HR02561","0":"A RESOLUTION DIRECTING THE COMMITTEE ON LABOR AND EMPLOYMENT TO CONDUCT AN INVESTIGATION, IN AID OF LEGISLATION, ON THE FAILURE OF COMMERCIAL ESTABLISHMENTS AND MALL OPERATORS TO PROPERLY EVACUATE THEIR WORKERS DURING THE APRIL 22, 2019 6.1-MAGNITUDE EARTHQUAKE","principal-authors":" BROSAS, ARLENE D.; DE JESUS, EMMI A.; ","primary-referral":" RULES","status":" Pending with the Committee on RULES since 2019-05-22","historyid":"#HR02561-17","docs":[{"doclabel":"[Text As Filed]","docurl":"congress.gov.ph\/legisdocs\/basic_17\/HR02561.pdf"}],"history":"\u003Ctable width=\"auto\"  border=\"0\" cellspacing=\"0\" cellpadding=\"0\"\u003E\u003Ctr\u003E\u003Ctd colspan=3\u003EHouse Bill\/Resolution NO. \u003Cb\u003EHR02561\u003C\/b\u003E\u003C\/td\u003E\u003C\/tr\u003E\u003Ctr\u003E\u003Ctd colspan=3\u003EFULL TITLE : A RESOLUTION DIRECTING THE COMMITTEE ON LABOR AND EMPLOYMENT TO CONDUCT AN INVESTIGATION, IN AID OF LEGISLATION, ON THE FAILURE OF COMMERCIAL ESTABLISHMENTS AND MALL OPERATORS TO PROPERLY EVACUATE THEIR WORKERS DURING THE APRIL 22, 2019 6.1-MAGNITUDE EARTHQUAKE\u003C\/td\u003E\u003C\/tr\u003E\u003Ctr\u003E\u003Ctd colspan=3\u003EPRINCIPAL AUTHOR\/S : \u003Cb\u003EBROSAS, ARLENE D., DE JESUS, EMMI A.\u003C\/b\u003E\u003C\/td\u003E\u003C\/tr\u003E\u003Ctr\u003E\u003Ctd colspan=3\u003EDATE FILED : 2019-05-21\u003C\/td\u003E\u003C\/tr\u003E\u003Ctr\u003E\u003Ctd colspan=3\u003E\u003Cb\u003EACTIONS TAKEN BY THE COMMITTEE ON RULES\u003C\/b\u003E\u003C\/td\u003E\u003C\/tr\u003E\u003Ctr\u003E\u003Ctd colspan=3\u003EREFERRAL TO THE COMMITTEE ON RULES ON 2019-05-22\u003C\/td\u003E\u003C\/tr\u003E\u003C\/table\u003E"}