{"heading":"HR01422","0":"A RESOLUTION COMMENDING AND CONGRATULATING THE UNIVERSITY OF THE PHILIPPINES (UP DILIMAN) COLLEGE OF LAW FOR WINNING THE 2017 NATIONAL MOOT COURT COMPETITION ON INTERNATIONAL HUMANITARIAN LAW (IHL) HELD AT THE UNIVERSITY OF THE PHILIPPINES BGC CAMPUS FROM OCTOBER 2 TO 6, 2017","principal-authors":" CASTELO, WINSTON \"WINNIE\"","primary-referral":" HIGHER AND TECHNICAL EDUCATION","mother-bill statusstatus":" Adopted as Resolution No. HR00196 on 2019-05-22 Substituted by HR02512","historyid":"#HR01422-17","docs":[{"doclabel":"[Text As Filed]","docurl":"congress.gov.ph\/legisdocs\/basic_17\/HR01422.pdf"}],"history":"\u003Ctable width=\"auto\"  border=\"0\" cellspacing=\"0\" cellpadding=\"0\"\u003E\u003Ctr\u003E\u003Ctd colspan=3\u003EHouse Bill\/Resolution NO. \u003Cb\u003EHR01422\u003C\/b\u003E\u003C\/td\u003E\u003C\/tr\u003E\u003Ctr\u003E\u003Ctd colspan=3\u003EFULL TITLE : A RESOLUTION COMMENDING AND CONGRATULATING THE UNIVERSITY OF THE PHILIPPINES (UP DILIMAN) COLLEGE OF LAW FOR WINNING THE 2017 NATIONAL MOOT COURT COMPETITION ON INTERNATIONAL HUMANITARIAN LAW (IHL) HELD AT THE UNIVERSITY OF THE PHILIPPINES BGC CAMPUS FROM OCTOBER 2 TO 6, 2017\u003C\/td\u003E\u003C\/tr\u003E\u003Ctr\u003E\u003Ctd colspan=3\u003EPRINCIPAL AUTHOR\/S : \u003Cb\u003ECASTELO, WINSTON &quot;WINNIE&quot;\u003C\/b\u003E\u003C\/td\u003E\u003C\/tr\u003E\u003Ctr\u003E\u003Ctd colspan=3\u003EDATE FILED : 2017-10-23\u003C\/td\u003E\u003C\/tr\u003E\u003Ctr\u003E\u003Ctd colspan=3\u003ECO-AUTHORS (Journal Entries) :\u003C\/td\u003E\u003C\/tr\u003E\u003Ctr\u003E\u003Ctd\u003E1. Belaro (000 2018-01-18)\u003C\/td\u003E\u003Ctr\u003E\u003Ctd colspan=3\u003E\u003Cb\u003EACTIONS TAKEN BY THE COMMITTEE\u003C\/b\u003E\u003C\/td\u003E\u003C\/tr\u003E\u003Ctr\u003E\u003Ctd colspan=3\u003EMOTHER BILL:&nbspHR02512\u003C\/td\u003E\u003C\/tr\u003E\u003Ctr\u003E\u003Ctd colspan=3\u003E\u003Cb\u003EACTIONS TAKEN BY THE COMMITTEE ON RULES\u003C\/b\u003E\u003C\/td\u003E\u003C\/tr\u003E\u003Ctr\u003E\u003Ctd colspan=3\u003EREFERRAL TO THE COMMITTEE ON HIGHER AND TECHNICAL EDUCATION ON 2017-11-20\u003C\/td\u003E\u003C\/tr\u003E\u003C\/table\u003E"}