{"heading":"PS00048","0":"Truth Behind Plaza Miranda Bombing","principal-authors":" ATIENZA, JOSE JR. L.","primary-referral":" RULES","status":" Pending with the Committee on RULES since 2016-08-22","historyid":"#PS00048-17","docs":[{"doclabel":"[Text As Filed]","docurl":"congress.gov.ph\/legisdocs\/basic_17\/PS048_Rep.%20Atienza.pdf"}],"history":"\u003Ctable width=\"auto\"  border=\"0\" cellspacing=\"0\" cellpadding=\"0\"\u003E\u003Ctr\u003E\u003Ctd colspan=3\u003EHouse Bill\/Resolution NO. \u003Cb\u003EPS00048\u003C\/b\u003E\u003C\/td\u003E\u003C\/tr\u003E\u003Ctr\u003E\u003Ctd colspan=3\u003EFULL TITLE : \u003C\/td\u003E\u003C\/tr\u003E\u003Ctr\u003E\u003Ctd colspan=3\u003ESHORT TITLE : Truth Behind Plaza Miranda Bombing\u003C\/td\u003E\u003C\/tr\u003E\u003Ctr\u003E\u003Ctd colspan=3\u003EABSTRACT : Rep. Atienza... stood up to speak on the same\r\nevent on August 21, 1971 wherein he, gladly stood up in front of the people in Plaza Miranda\r\nto be proclaimed as candidates of the Liberal Party when the bombing took place; averred that the years in between have shown that the late former Pres. Ferdinand E. Marcos had nothing to do with said bombing, and that acc. to research,...it was Jose Maria Sison who masterminded the whole thing...; spoke about the assassination of former Senator Benigno \u201cNinoy\u201d Aquino Jr. also on August 21 and wondered why despite having had two Aquino Administrations, no one seemed interested in\r\nspeaking about the issues during said administrations,...; expressed his support for the burial of former Pres. Marcos in the Libingan ng mga Bayani...(House Journal No.13,p.12-13)\u003C\/td\u003E\u003C\/tr\u003E\u003Ctr\u003E\u003Ctd colspan=3\u003EPRINCIPAL AUTHOR\/S : \u003Cb\u003EATIENZA, JOSE JR. L.\u003C\/b\u003E\u003C\/td\u003E\u003C\/tr\u003E\u003Ctr\u003E\u003Ctd colspan=3\u003EDATE FILED : 2016-08-22\u003C\/td\u003E\u003C\/tr\u003E\u003Ctr\u003E\u003Ctd colspan=3\u003ESIGNIFICANCE: NATIONAL\u003C\/td\u003E\u003C\/tr\u003E\u003Ctr\u003E\u003Ctd colspan=3\u003ENATURE : Speech-Privilege Hour\u003C\/td\u003E\u003C\/tr\u003E\u003Ctr\u003E\u003Ctd colspan=3\u003E\u003Cb\u003EACTIONS TAKEN BY THE COMMITTEE ON RULES\u003C\/b\u003E\u003C\/td\u003E\u003C\/tr\u003E\u003Ctr\u003E\u003Ctd colspan=3\u003EREFERRAL TO THE COMMITTEE ON RULES ON 2016-08-22\u003C\/td\u003E\u003C\/tr\u003E\u003C\/table\u003E"}